sodasql/__main__.py
sodasql/__version__.py
sodasql/dataset_analyzer.py
sodasql/cli/__init__.py
sodasql/cli/cli.py
sodasql/cli/indenting_yaml_dumper.py
sodasql/cli/ingest.py
sodasql/common/config_helper.py
sodasql/common/json_helper.py
sodasql/common/logging_helper.py
sodasql/common/yaml_helper.py
sodasql/exceptions/exceptions.py
sodasql/scan/column_metadata.py
sodasql/scan/db.py
sodasql/scan/dialect.py
sodasql/scan/dialect_parser.py
sodasql/scan/env_vars.py
sodasql/scan/failed_rows_processor.py
sodasql/scan/file_system.py
sodasql/scan/group_value.py
sodasql/scan/historic_metric_yml.py
sodasql/scan/measurement.py
sodasql/scan/metric.py
sodasql/scan/missing.py
sodasql/scan/parser.py
sodasql/scan/sampler.py
sodasql/scan/samples_yml.py
sodasql/scan/scan.py
sodasql/scan/scan_builder.py
sodasql/scan/scan_column.py
sodasql/scan/scan_error.py
sodasql/scan/scan_result.py
sodasql/scan/scan_yml.py
sodasql/scan/scan_yml_column.py
sodasql/scan/scan_yml_parser.py
sodasql/scan/sql_metric_yml.py
sodasql/scan/test.py
sodasql/scan/test_result.py
sodasql/scan/warehouse.py
sodasql/scan/warehouse_yml.py
sodasql/scan/warehouse_yml_parser.py
sodasql/scan/validity/__init__.py
sodasql/scan/validity/money_patterns.py
sodasql/soda_server_client/monitor_measurement.py
sodasql/soda_server_client/monitor_metric.py
sodasql/soda_server_client/monitor_metric_parser.py
sodasql/soda_server_client/soda_server_client.py
sodasql/telemetry/memory_span_exporter.py
sodasql/telemetry/soda_exporter.py
sodasql/telemetry/soda_telemetry.py
sodasql/telemetry/soda_tracer.py
soda_sql_core-2.2.2.dist-info/METADATA
soda_sql_core-2.2.2.dist-info/WHEEL
soda_sql_core-2.2.2.dist-info/entry_points.txt
soda_sql_core-2.2.2.dist-info/top_level.txt
soda_sql_core-2.2.2.dist-info/RECORD
