Metadata-Version: 2.1
Name: soda-sql-core
Version: 2.2.2
Summary: Soda SQL library & CLI
Author: Tom Baeyens
Author-email: tom@soda.io
Classifier: Development Status :: 5 - Production/Stable
Classifier: License :: OSI Approved :: Apache Software License
Classifier: Operating System :: Microsoft :: Windows
Classifier: Operating System :: MacOS :: MacOS X
Classifier: Operating System :: POSIX :: Linux
Classifier: Programming Language :: Python :: 3.7
Classifier: Programming Language :: Python :: 3.8
Classifier: Programming Language :: Python :: 3.9
Requires-Python: >=3.7
Requires-Dist: markupsafe (==2.0.1)
Requires-Dist: Jinja2 (<4.0,>=2.11.3)
Requires-Dist: click (<9.0,>=8.0)
Requires-Dist: pyyaml (<6.0,>=5.4.1)
Requires-Dist: requests (<3.0,>=2.23.0)
Requires-Dist: Deprecated (<1.3,>=1.2.13)
Requires-Dist: opentelemetry-api (~=1.11.0)
Requires-Dist: opentelemetry-exporter-otlp-proto-http (~=1.11.0)
Requires-Dist: protobuf (~=3.19.0)
